LICENSE
MANIFEST.in
README.md
reconic.py
setup.py
reconic1.egg-info/PKG-INFO
reconic1.egg-info/SOURCES.txt
reconic1.egg-info/dependency_links.txt
reconic1.egg-info/entry_points.txt
reconic1.egg-info/requires.txt
reconic1.egg-info/top_level.txt
src/__init__.py
src/directory_scan.py
src/dns_scan.py
src/http_headers.py
src/js_scan.py
src/port_scanner.py
src/report_generator.py
src/ssl_scan.py
src/subdomain_scan.py
src/textwrap.py
src/whois_lookup.py
templates/report_template.html
utils/ports.json
utils/utils.py
utils/__pycache__/utils.cpython-311.pyc
wordlists/directories.txt
wordlists/subdomains.txt