Metadata-Version: 2.1
Name: reconic1
Version: 1.7.0
Summary: All-in-One Reconnaissance Tool for Penetration Testing and Bounty Hunting
Home-page: https://github.com/fkkarakurt/reconic
Author: Fatih Küçükkarakurt
Author-email: fatihkkarakurt128@gmail.com
Keywords: recon tool
Classifier: Development Status :: 5 - Production/Stable
Classifier: Environment :: Console
Classifier: Intended Audience :: Information Technology
Classifier: Intended Audience :: System Administrators
Classifier: Intended Audience :: Telecommunications Industry
Classifier: Programming Language :: Python :: 3
Classifier: License :: OSI Approved :: MIT License
Classifier: Operating System :: POSIX :: Linux
Classifier: Topic :: Security
Requires-Python: >=3.8
License-File: LICENSE
